docs/Makefile
docs/make.bat
docs/source/conf.py
docs/source/index.rst
docs/source/modules.rst
docs/source/pygbm.cli.rst
docs/source/pygbm.gbm_simulator.rst
docs/source/pygbm.rst
docs/source/pygbm.version.rst
pygbm/__init__.py
pygbm/cli.py
pygbm/gbm_simulator.py
pygbm/version.py
pygbm/data/example_fig.png
pygbm_dec52-0.1.1.post6.dist-info/licenses/LICENSE
tests/test_gbm.py
pygbm_dec52-0.1.1.post6.dist-info/METADATA
pygbm_dec52-0.1.1.post6.dist-info/WHEEL
pygbm_dec52-0.1.1.post6.dist-info/entry_points.txt
pygbm_dec52-0.1.1.post6.dist-info/top_level.txt
pygbm_dec52-0.1.1.post6.dist-info/RECORD
