Metadata-Version: 2.4
Name: pygbm-dec52
Version: 0.1.1.post6
Summary: A Python package for modelling geometric Brownian motions.
Author-email: David Chen <dec52@cam.ac.uk>
Requires-Python: >=3.9
License-File: LICENSE
Requires-Dist: numpy
Requires-Dist: matplotlib
Requires-Dist: argparse
Dynamic: license-file
